[
  {
    "exchange": "belo",
    "moneda": "ARS",
    "monedaBase": "MEXt",
    "compra": 91.05239013167306,
    "venta": 87.46962617283951
  },
  {
    "exchange": "belo",
    "moneda": "BRAt",
    "monedaBase": "MEXt",
    "compra": 0.30874086309015575,
    "venta": 0.2947715086419753
  },
  {
    "exchange": "belo",
    "moneda": "ARGt",
    "monedaBase": "MEXt",
    "compra": 91.05239013167306,
    "venta": 87.46962617283951
  },
  {
    "exchange": "belo",
    "moneda": "MEXt",
    "monedaBase": "MEXt",
    "compra": 1,
    "venta": 1
  },
  {
    "exchange": "belo",
    "moneda": "CHLt",
    "monedaBase": "MEXt",
    "compra": 54.4146114416689,
    "venta": 51.442604974232594
  },
  {
    "exchange": "belo",
    "moneda": "COLt",
    "monedaBase": "MEXt",
    "compra": 203.34385626234933,
    "venta": 192.01285236256172
  },
  {
    "exchange": "belo",
    "moneda": "BOLt",
    "monedaBase": "MEXt",
    "compra": 0.5822251158590088,
    "venta": 0.5497993948655864
  },
  {
    "exchange": "belo",
    "moneda": "PERt",
    "monedaBase": "MEXt",
    "compra": 0.20049409902601192,
    "venta": 0.1884048222222222
  }
]