[
  {
    "exchange": "belo",
    "moneda": "ARS",
    "monedaBase": "MEXt",
    "compra": 89.69160741076554,
    "venta": 86.16083861728396
  },
  {
    "exchange": "belo",
    "moneda": "BRAt",
    "monedaBase": "MEXt",
    "compra": 0.3065928802341855,
    "venta": 0.29328921224691357
  },
  {
    "exchange": "belo",
    "moneda": "ARGt",
    "monedaBase": "MEXt",
    "compra": 89.69160741076554,
    "venta": 86.16083861728396
  },
  {
    "exchange": "belo",
    "moneda": "MEXt",
    "monedaBase": "MEXt",
    "compra": 1,
    "venta": 1
  },
  {
    "exchange": "belo",
    "moneda": "CHLt",
    "monedaBase": "MEXt",
    "compra": 53.74533915110038,
    "venta": 50.817473718820935
  },
  {
    "exchange": "belo",
    "moneda": "COLt",
    "monedaBase": "MEXt",
    "compra": 202.82511002699812,
    "venta": 190.13622500307886
  },
  {
    "exchange": "belo",
    "moneda": "BOLt",
    "monedaBase": "MEXt",
    "compra": 0.5941410082643642,
    "venta": 0.5612123669065494
  },
  {
    "exchange": "belo",
    "moneda": "PERt",
    "monedaBase": "MEXt",
    "compra": 0.20214470906190116,
    "venta": 0.1882985214814815
  }
]