[
  {
    "moneda": "ARS",
    "nombre": "Peso Argentino",
    "compra": 0.6,
    "venta": 0.64,
    "ultimoCierre": 0.62,
    "fechaActualizacion": "2026-06-24T20:01:16.660Z"
  },
  {
    "moneda": "USD",
    "nombre": "Dólar",
    "compra": 919.51,
    "venta": 920.59,
    "ultimoCierre": 913.38,
    "fechaActualizacion": "2026-06-24T20:01:20.070Z"
  },
  {
    "moneda": "EUR",
    "nombre": "Euro",
    "compra": 1006.48,
    "venta": 1066.68,
    "ultimoCierre": 1033.32,
    "fechaActualizacion": "2026-06-24T20:01:22.234Z"
  },
  {
    "moneda": "BRL",
    "nombre": "Real Brasileño",
    "compra": 176.965,
    "venta": 177.173,
    "ultimoCierre": 176.506,
    "fechaActualizacion": "2026-06-24T20:01:11.707Z"
  },
  {
    "moneda": "UYU",
    "nombre": "Peso Uruguayo",
    "compra": 23.04,
    "venta": 23.07,
    "ultimoCierre": 22.75,
    "fechaActualizacion": "2026-06-24T20:01:11.233Z"
  }
]