[
  {
    "exchange": "belo",
    "moneda": "ARS",
    "monedaBase": "BTC",
    "compra": 93383873.4363,
    "venta": 90304839.9
  },
  {
    "exchange": "belo",
    "moneda": "BRAt",
    "monedaBase": "BTC",
    "compra": 317313.228231,
    "venta": 305172.3114
  },
  {
    "exchange": "belo",
    "moneda": "ARGt",
    "monedaBase": "BTC",
    "compra": 93383873.4363,
    "venta": 90304839.9
  },
  {
    "exchange": "belo",
    "moneda": "MEXt",
    "monedaBase": "BTC",
    "compra": 1056647.1538335797,
    "venta": 1008089.0031661812
  },
  {
    "exchange": "belo",
    "moneda": "CHLt",
    "monedaBase": "BTC",
    "compra": 55694322.354492486,
    "venta": 53030158.02657243
  },
  {
    "exchange": "belo",
    "moneda": "COLt",
    "monedaBase": "BTC",
    "compra": 209351375.30275768,
    "venta": 197632202.7425625
  },
  {
    "exchange": "belo",
    "moneda": "BOLt",
    "monedaBase": "BTC",
    "compra": 597785.8817781867,
    "venta": 568623.14546895
  },
  {
    "exchange": "belo",
    "moneda": "PERt",
    "monedaBase": "BTC",
    "compra": 206060.93137931035,
    "venta": 195052.5522
  },
  {
    "exchange": "belo",
    "moneda": "ETH",
    "monedaBase": "BTC",
    "compra": 37.888259943773825,
    "venta": 37.12407236224185
  },
  {
    "exchange": "belo",
    "moneda": "USD",
    "monedaBase": "BTC",
    "criptomoneda": "USDT",
    "criptomonedaBase": null,
    "compra": 59757.6701,
    "venta": 58574.34
  },
  {
    "exchange": "belo",
    "moneda": "USD",
    "monedaBase": "BTC",
    "criptomoneda": "USDC",
    "criptomonedaBase": null,
    "compra": 59676.759,
    "venta": 58495.0311
  },
  {
    "exchange": "belo",
    "moneda": "SOL",
    "monedaBase": "BTC",
    "compra": 814.5319007346263,
    "venta": 798.3381792460814
  },
  {
    "exchange": "belo",
    "moneda": "BRAt",
    "monedaBase": "BTC",
    "compra": 317313.228231,
    "venta": 305172.3114
  }
]