[
  {
    "exchange": "belo",
    "moneda": "ARS",
    "monedaBase": "BTC",
    "compra": 100223279.7,
    "venta": 96928796.844
  },
  {
    "exchange": "belo",
    "moneda": "BRAt",
    "monedaBase": "BTC",
    "compra": 342095.461376,
    "venta": 330736.773015
  },
  {
    "exchange": "belo",
    "moneda": "ARGt",
    "monedaBase": "BTC",
    "compra": 100223279.7,
    "venta": 96928796.844
  },
  {
    "exchange": "belo",
    "moneda": "MEXt",
    "monedaBase": "BTC",
    "compra": 1162938.1243098325,
    "venta": 1109539.9235264454
  },
  {
    "exchange": "belo",
    "moneda": "CHLt",
    "monedaBase": "BTC",
    "compra": 60042396.879271775,
    "venta": 57170512.91854188
  },
  {
    "exchange": "belo",
    "moneda": "COLt",
    "monedaBase": "BTC",
    "compra": 231906759.03815827,
    "venta": 218924487.6494445
  },
  {
    "exchange": "belo",
    "moneda": "BOLt",
    "monedaBase": "BTC",
    "compra": 668308.5594914843,
    "venta": 635705.41493745
  },
  {
    "exchange": "belo",
    "moneda": "PERt",
    "monedaBase": "BTC",
    "compra": 230370.58655172415,
    "venta": 216753.8274
  },
  {
    "exchange": "belo",
    "moneda": "ETH",
    "monedaBase": "BTC",
    "compra": 37.12241859981661,
    "venta": 36.37395333949266
  },
  {
    "exchange": "belo",
    "moneda": "USD",
    "monedaBase": "BTC",
    "criptomoneda": "USDT",
    "criptomonedaBase": null,
    "compra": 66815.5198,
    "venta": 65492.4303
  },
  {
    "exchange": "belo",
    "moneda": "USD",
    "monedaBase": "BTC",
    "criptomoneda": "USDC",
    "criptomonedaBase": null,
    "compra": 66769.484,
    "venta": 65447.3061
  },
  {
    "exchange": "belo",
    "moneda": "SOL",
    "monedaBase": "BTC",
    "compra": 901.9564337003394,
    "venta": 884.016973125884
  },
  {
    "exchange": "belo",
    "moneda": "BRAt",
    "monedaBase": "BTC",
    "compra": 342095.461376,
    "venta": 330736.773015
  }
]