[
  {
    "exchange": "belo",
    "moneda": "ARS",
    "monedaBase": "SOL",
    "compra": 110274.1432,
    "venta": 106578.4005
  },
  {
    "exchange": "belo",
    "moneda": "BRAt",
    "monedaBase": "SOL",
    "compra": 374.61203,
    "venta": 362.865591
  },
  {
    "exchange": "belo",
    "moneda": "ARGt",
    "monedaBase": "SOL",
    "compra": 110274.1432,
    "venta": 106578.4005
  },
  {
    "exchange": "belo",
    "moneda": "MEXt",
    "monedaBase": "SOL",
    "compra": 1274.0914051905468,
    "venta": 1215.1117415732624
  },
  {
    "exchange": "belo",
    "moneda": "CHLt",
    "monedaBase": "SOL",
    "compra": 65679.8584728985,
    "venta": 62529.80097329955
  },
  {
    "exchange": "belo",
    "moneda": "COLt",
    "monedaBase": "SOL",
    "compra": 254762.81097539878,
    "venta": 240468.2127478125
  },
  {
    "exchange": "belo",
    "moneda": "BOLt",
    "monedaBase": "SOL",
    "compra": 724.5094046297793,
    "venta": 689.0689038915
  },
  {
    "exchange": "belo",
    "moneda": "PERt",
    "monedaBase": "SOL",
    "compra": 250.75862068965517,
    "venta": 235.19133
  },
  {
    "exchange": "belo",
    "moneda": "BRAt",
    "monedaBase": "SOL",
    "compra": 374.61203,
    "venta": 362.865591
  }
]