[
  {
    "exchange": "belo",
    "moneda": "ARS",
    "monedaBase": "SOL",
    "compra": 112602.2942,
    "venta": 109204.0785
  },
  {
    "exchange": "belo",
    "moneda": "BRAt",
    "monedaBase": "SOL",
    "compra": 384.657086,
    "venta": 369.4197375
  },
  {
    "exchange": "belo",
    "moneda": "ARGt",
    "monedaBase": "SOL",
    "compra": 112602.2942,
    "venta": 109204.0785
  },
  {
    "exchange": "belo",
    "moneda": "MEXt",
    "monedaBase": "SOL",
    "compra": 1292.6078608832584,
    "venta": 1233.7969190807712
  },
  {
    "exchange": "belo",
    "moneda": "CHLt",
    "monedaBase": "SOL",
    "compra": 67597.60763595763,
    "venta": 64358.81850038355
  },
  {
    "exchange": "belo",
    "moneda": "COLt",
    "monedaBase": "SOL",
    "compra": 255726.4852335165,
    "venta": 241379.68992946876
  },
  {
    "exchange": "belo",
    "moneda": "BOLt",
    "monedaBase": "SOL",
    "compra": 740.2074845815687,
    "venta": 704.000220375375
  },
  {
    "exchange": "belo",
    "moneda": "PERt",
    "monedaBase": "SOL",
    "compra": 253.61448275862068,
    "venta": 238.591089
  },
  {
    "exchange": "belo",
    "moneda": "BRAt",
    "monedaBase": "SOL",
    "compra": 384.657086,
    "venta": 369.4197375
  }
]