[
  {
    "exchange": "belo",
    "moneda": "ARS",
    "monedaBase": "USD",
    "criptomoneda": null,
    "criptomonedaBase": "USDT",
    "compra": 1550,
    "venta": 1531
  },
  {
    "exchange": "belo",
    "moneda": "ARS",
    "monedaBase": "USD",
    "criptomoneda": null,
    "criptomonedaBase": "USDC",
    "compra": 1554.063604,
    "venta": 1530.400360885
  },
  {
    "exchange": "belo",
    "moneda": "ARS",
    "monedaBase": "USD",
    "criptomoneda": null,
    "criptomonedaBase": "USD_AR",
    "compra": 1519.6078431372548,
    "venta": 1456.707897240723
  },
  {
    "exchange": "dolarapp",
    "moneda": "ARS",
    "monedaBase": "USD",
    "criptomoneda": null,
    "criptomonedaBase": "USDC",
    "compra": 1540.78,
    "venta": 1534.73373
  },
  {
    "exchange": "satoshitango",
    "moneda": "ARS",
    "monedaBase": "USD",
    "criptomoneda": null,
    "criptomonedaBase": "USDT",
    "compra": 1541.71,
    "venta": null
  },
  {
    "exchange": "satoshitango",
    "moneda": "ARS",
    "monedaBase": "USD",
    "criptomoneda": null,
    "criptomonedaBase": "USD",
    "compra": 1448.98,
    "venta": null
  }
]