[
  {
    "exchange": "belo",
    "moneda": "ARS",
    "monedaBase": "USD",
    "criptomoneda": null,
    "criptomonedaBase": "USDT",
    "compra": 1560,
    "venta": 1544
  },
  {
    "exchange": "belo",
    "moneda": "ARS",
    "monedaBase": "USD",
    "criptomoneda": null,
    "criptomonedaBase": "USDC",
    "compra": 1564.1054442,
    "venta": 1543.41068608
  },
  {
    "exchange": "belo",
    "moneda": "BRAt",
    "monedaBase": "USD",
    "criptomoneda": null,
    "criptomonedaBase": "USDT",
    "compra": 5.31,
    "venta": 5.25
  },
  {
    "exchange": "belo",
    "moneda": "BRAt",
    "monedaBase": "USD",
    "criptomoneda": null,
    "criptomonedaBase": "USDC",
    "compra": 5.32397430045,
    "venta": 5.24799618
  },
  {
    "exchange": "belo",
    "moneda": "ARGt",
    "monedaBase": "USD",
    "criptomoneda": null,
    "criptomonedaBase": "USDT",
    "compra": 1560,
    "venta": 1544
  },
  {
    "exchange": "belo",
    "moneda": "ARGt",
    "monedaBase": "USD",
    "criptomoneda": null,
    "criptomonedaBase": "USDC",
    "compra": 1564.1054442,
    "venta": 1543.41068608
  },
  {
    "exchange": "belo",
    "moneda": "MEXt",
    "monedaBase": "USD",
    "criptomoneda": null,
    "criptomonedaBase": "USDT",
    "compra": 17.760060789399184,
    "venta": 17.28641401275
  },
  {
    "exchange": "belo",
    "moneda": "MEXt",
    "monedaBase": "USD",
    "criptomoneda": null,
    "criptomonedaBase": "USDC",
    "compra": 17.80679985257834,
    "venta": 17.279816134249614
  },
  {
    "exchange": "belo",
    "moneda": "CHLt",
    "monedaBase": "USD",
    "criptomoneda": null,
    "criptomonedaBase": "USDT",
    "compra": 930.9745579594877,
    "venta": 904.5020865
  },
  {
    "exchange": "belo",
    "moneda": "CHLt",
    "monedaBase": "USD",
    "criptomoneda": null,
    "criptomonedaBase": "USDC",
    "compra": 933.4245990487968,
    "venta": 904.1568561436247
  },
  {
    "exchange": "belo",
    "moneda": "COLt",
    "monedaBase": "USD",
    "criptomoneda": null,
    "criptomonedaBase": "USDT",
    "compra": 3471.3888984125897,
    "venta": 3368.71553125
  },
  {
    "exchange": "belo",
    "moneda": "COLt",
    "monedaBase": "USD",
    "criptomoneda": null,
    "criptomonedaBase": "USDC",
    "compra": 3480.5245352195975,
    "venta": 3367.4297599060324
  },
  {
    "exchange": "belo",
    "moneda": "BOLt",
    "monedaBase": "USD",
    "criptomoneda": null,
    "criptomonedaBase": "USDT",
    "compra": 9.963000613720839,
    "venta": 9.668415
  },
  {
    "exchange": "belo",
    "moneda": "BOLt",
    "monedaBase": "USD",
    "criptomoneda": null,
    "criptomonedaBase": "USDC",
    "compra": 9.989220192620964,
    "venta": 9.6647247593628
  },
  {
    "exchange": "belo",
    "moneda": "PERt",
    "monedaBase": "USD",
    "criptomoneda": null,
    "criptomonedaBase": "USDT",
    "compra": 3.4482758620689653,
    "venta": 3.33
  },
  {
    "exchange": "belo",
    "moneda": "PERt",
    "monedaBase": "USD",
    "criptomoneda": null,
    "criptomonedaBase": "USDC",
    "compra": 3.457350672413793,
    "venta": 3.3287290056
  },
  {
    "exchange": "belo",
    "moneda": "USD",
    "monedaBase": "USD",
    "criptomoneda": "USDC",
    "criptomonedaBase": "USDT",
    "compra": 1.0003818257352466,
    "venta": 0.997375212639772
  },
  {
    "exchange": "belo",
    "moneda": "SOL",
    "monedaBase": "USD",
    "criptomoneda": null,
    "criptomonedaBase": "USDT",
    "compra": 0.015302242237555068,
    "venta": 0.014996955618009544
  },
  {
    "exchange": "belo",
    "moneda": "BRAt",
    "monedaBase": "USD",
    "criptomoneda": null,
    "criptomonedaBase": "USDT",
    "compra": 5.31,
    "venta": 5.25
  },
  {
    "exchange": "belo",
    "moneda": "SOL",
    "monedaBase": "USD",
    "criptomoneda": null,
    "criptomonedaBase": "USDC",
    "compra": 0.015320810103155015,
    "venta": 0.015015150286639219
  },
  {
    "exchange": "belo",
    "moneda": "BRAt",
    "monedaBase": "USD",
    "criptomoneda": null,
    "criptomonedaBase": "USDC",
    "compra": 5.32397430045,
    "venta": 5.24799618
  },
  {
    "exchange": "belo",
    "moneda": "USD",
    "monedaBase": "USD",
    "criptomoneda": "USDT",
    "criptomonedaBase": "USD",
    "compra": 1,
    "venta": 1
  },
  {
    "exchange": "belo",
    "moneda": "USD",
    "monedaBase": "USD",
    "criptomoneda": "USD_AR",
    "criptomonedaBase": "USDT",
    "compra": 1.05,
    "venta": 1.02
  },
  {
    "exchange": "belo",
    "moneda": "ARS",
    "monedaBase": "USD",
    "criptomoneda": null,
    "criptomonedaBase": "USD_AR",
    "compra": 1529.4117647058824,
    "venta": 1470.4761904761904
  }
]