[
  {
    "exchange": "belo",
    "moneda": "ARS",
    "monedaBase": "USD",
    "criptomoneda": null,
    "criptomonedaBase": "USDT",
    "compra": 1547,
    "venta": 1527
  },
  {
    "exchange": "belo",
    "moneda": "ARS",
    "monedaBase": "USD",
    "criptomoneda": null,
    "criptomonedaBase": "USDC",
    "compra": 1550.71488845,
    "venta": 1526.066491455
  },
  {
    "exchange": "belo",
    "moneda": "BRAt",
    "monedaBase": "USD",
    "criptomoneda": null,
    "criptomonedaBase": "USDT",
    "compra": 5.26,
    "venta": 5.15
  },
  {
    "exchange": "belo",
    "moneda": "BRAt",
    "monedaBase": "USD",
    "criptomoneda": null,
    "criptomonedaBase": "USDC",
    "compra": 5.272631101,
    "venta": 5.14685162475
  },
  {
    "exchange": "belo",
    "moneda": "ARGt",
    "monedaBase": "USD",
    "criptomoneda": null,
    "criptomonedaBase": "USDT",
    "compra": 1547,
    "venta": 1527
  },
  {
    "exchange": "belo",
    "moneda": "ARGt",
    "monedaBase": "USD",
    "criptomoneda": null,
    "criptomonedaBase": "USDC",
    "compra": 1550.71488845,
    "venta": 1526.066491455
  },
  {
    "exchange": "belo",
    "moneda": "MEXt",
    "monedaBase": "USD",
    "criptomoneda": null,
    "criptomonedaBase": "USDT",
    "compra": 17.747070331157705,
    "venta": 17.27425263425
  },
  {
    "exchange": "belo",
    "moneda": "MEXt",
    "monedaBase": "USD",
    "criptomoneda": null,
    "criptomonedaBase": "USDC",
    "compra": 17.78968725849743,
    "venta": 17.263692279015842
  },
  {
    "exchange": "belo",
    "moneda": "CHLt",
    "monedaBase": "USD",
    "criptomoneda": null,
    "criptomonedaBase": "USDT",
    "compra": 927.3846379307187,
    "venta": 900.8629515
  },
  {
    "exchange": "belo",
    "moneda": "CHLt",
    "monedaBase": "USD",
    "criptomoneda": null,
    "criptomonedaBase": "USDC",
    "compra": 929.6116130310136,
    "venta": 900.3122224475447
  },
  {
    "exchange": "belo",
    "moneda": "COLt",
    "monedaBase": "USD",
    "criptomoneda": null,
    "criptomonedaBase": "USDT",
    "compra": 3481.0561782300765,
    "venta": 3378.049875
  },
  {
    "exchange": "belo",
    "moneda": "COLt",
    "monedaBase": "USD",
    "criptomoneda": null,
    "criptomonedaBase": "USDC",
    "compra": 3489.415412483669,
    "venta": 3375.984754879667
  },
  {
    "exchange": "belo",
    "moneda": "BOLt",
    "monedaBase": "USD",
    "criptomoneda": null,
    "criptomonedaBase": "USDT",
    "compra": 10.023750100237502,
    "venta": 9.72736875
  },
  {
    "exchange": "belo",
    "moneda": "BOLt",
    "monedaBase": "USD",
    "criptomoneda": null,
    "criptomonedaBase": "USDC",
    "compra": 10.047820632540706,
    "venta": 9.721422069025218
  },
  {
    "exchange": "belo",
    "moneda": "PERt",
    "monedaBase": "USD",
    "criptomoneda": null,
    "criptomonedaBase": "USDT",
    "compra": 3.4482758620689653,
    "venta": 3.33
  },
  {
    "exchange": "belo",
    "moneda": "PERt",
    "monedaBase": "USD",
    "criptomoneda": null,
    "criptomonedaBase": "USDC",
    "compra": 3.456556379310345,
    "venta": 3.32796425445
  },
  {
    "exchange": "belo",
    "moneda": "USD",
    "monedaBase": "USD",
    "criptomoneda": "USDC",
    "criptomonedaBase": "USDT",
    "compra": 1.0006117089590965,
    "venta": 0.997604402667654
  },
  {
    "exchange": "belo",
    "moneda": "SOL",
    "monedaBase": "USD",
    "criptomoneda": null,
    "criptomonedaBase": "USDT",
    "compra": 0.014624308818604461,
    "venta": 0.014332643455428345
  },
  {
    "exchange": "belo",
    "moneda": "BRAt",
    "monedaBase": "USD",
    "criptomoneda": null,
    "criptomonedaBase": "USDT",
    "compra": 5.26,
    "venta": 5.15
  },
  {
    "exchange": "belo",
    "moneda": "SOL",
    "monedaBase": "USD",
    "criptomoneda": null,
    "criptomonedaBase": "USDC",
    "compra": 0.014630663529852405,
    "venta": 0.014338870527168575
  },
  {
    "exchange": "belo",
    "moneda": "BRAt",
    "monedaBase": "USD",
    "criptomoneda": null,
    "criptomonedaBase": "USDC",
    "compra": 5.272631101,
    "venta": 5.14685162475
  },
  {
    "exchange": "belo",
    "moneda": "USD",
    "monedaBase": "USD",
    "criptomoneda": "USDT",
    "criptomonedaBase": "USD",
    "compra": 1,
    "venta": 1
  },
  {
    "exchange": "belo",
    "moneda": "USD",
    "monedaBase": "USD",
    "criptomoneda": "USD_AR",
    "criptomonedaBase": "USDT",
    "compra": 1.057,
    "venta": 1.026
  },
  {
    "exchange": "belo",
    "moneda": "ARS",
    "monedaBase": "USD",
    "criptomoneda": null,
    "criptomonedaBase": "USD_AR",
    "compra": 1507.7972709551657,
    "venta": 1444.6546830652792
  }
]