[
  {
    "exchange": "belo",
    "moneda": "ARS",
    "monedaBase": "BRAt",
    "compra": 298.83268482490274,
    "venta": 288.76190476190476
  },
  {
    "exchange": "belo",
    "moneda": "BRAt",
    "monedaBase": "BRAt",
    "compra": 1,
    "venta": 1
  },
  {
    "exchange": "belo",
    "moneda": "ARGt",
    "monedaBase": "BRAt",
    "compra": 298.83268482490274,
    "venta": 288.76190476190476
  },
  {
    "exchange": "belo",
    "moneda": "MEXt",
    "monedaBase": "BRAt",
    "compra": 3.4412594501946714,
    "venta": 3.2805029885714285
  },
  {
    "exchange": "belo",
    "moneda": "CHLt",
    "monedaBase": "BRAt",
    "compra": 180.33748276374413,
    "venta": 171.4973982857143
  },
  {
    "exchange": "belo",
    "moneda": "COLt",
    "monedaBase": "BRAt",
    "compra": 675.6686416878142,
    "venta": 637.1020833333333
  },
  {
    "exchange": "belo",
    "moneda": "BOLt",
    "monedaBase": "BRAt",
    "compra": 1.9560555356889218,
    "venta": 1.8584467857142857
  },
  {
    "exchange": "belo",
    "moneda": "PERt",
    "monedaBase": "BRAt",
    "compra": 0.670870790285791,
    "venta": 0.6304761904761905
  }
]