[
  {
    "exchange": "belo",
    "moneda": "ARS",
    "monedaBase": "BRAt",
    "compra": 300.9596928982726,
    "venta": 291.52542372881356
  },
  {
    "exchange": "belo",
    "moneda": "BRAt",
    "monedaBase": "BRAt",
    "compra": 1,
    "venta": 1
  },
  {
    "exchange": "belo",
    "moneda": "ARGt",
    "monedaBase": "BRAt",
    "compra": 300.9596928982726,
    "venta": 291.52542372881356
  },
  {
    "exchange": "belo",
    "moneda": "MEXt",
    "monedaBase": "BRAt",
    "compra": 3.396286899475171,
    "venta": 3.243546515089454
  },
  {
    "exchange": "belo",
    "moneda": "CHLt",
    "monedaBase": "BRAt",
    "compra": 179.3528788705569,
    "venta": 170.94321271186442
  },
  {
    "exchange": "belo",
    "moneda": "COLt",
    "monedaBase": "BRAt",
    "compra": 670.0841731611335,
    "venta": 638.0179849340866
  },
  {
    "exchange": "belo",
    "moneda": "BOLt",
    "monedaBase": "BRAt",
    "compra": 1.9239443570513437,
    "venta": 1.831896186440678
  },
  {
    "exchange": "belo",
    "moneda": "PERt",
    "monedaBase": "BRAt",
    "compra": 0.6618571712224502,
    "venta": 0.6271186440677966
  }
]