[
  {
    "exchange": "belo",
    "moneda": "ARS",
    "monedaBase": "CHLt",
    "compra": 1.7293565586920372,
    "venta": 1.6577925925925925
  },
  {
    "exchange": "belo",
    "moneda": "BRAt",
    "monedaBase": "CHLt",
    "compra": 0.005825201039804757,
    "venta": 0.005581235061728395
  },
  {
    "exchange": "belo",
    "moneda": "ARGt",
    "monedaBase": "CHLt",
    "compra": 1.7293565586920372,
    "venta": 1.6577925925925925
  },
  {
    "exchange": "belo",
    "moneda": "MEXt",
    "monedaBase": "CHLt",
    "compra": 0.0198368027010925,
    "venta": 0.018756087503296593
  },
  {
    "exchange": "belo",
    "moneda": "CHLt",
    "monedaBase": "CHLt",
    "compra": 1,
    "venta": 1
  },
  {
    "exchange": "belo",
    "moneda": "COLt",
    "monedaBase": "CHLt",
    "compra": 3.9813239106689444,
    "venta": 3.7247698591205247
  },
  {
    "exchange": "belo",
    "moneda": "BOLt",
    "monedaBase": "CHLt",
    "compra": 0.011381328402748265,
    "venta": 0.010728921441654321
  },
  {
    "exchange": "belo",
    "moneda": "PERt",
    "monedaBase": "CHLt",
    "compra": 0.003923222683058161,
    "venta": 0.0036581956543209875
  }
]