[
  {
    "exchange": "belo",
    "moneda": "ARS",
    "monedaBase": "BRL",
    "compra": 307.90211946050096,
    "venta": 289.07721280602635
  },
  {
    "exchange": "fiwind",
    "moneda": "ARS",
    "monedaBase": "BRL",
    "compra": 303.201674,
    "venta": 283.156846
  },
  {
    "exchange": "dolarapp",
    "moneda": "ARS",
    "monedaBase": "BRL",
    "compra": 302.1451718460363,
    "venta": null
  },
  {
    "exchange": "satoshitango",
    "moneda": "ARS",
    "monedaBase": "BRL",
    "compra": 304.52,
    "venta": null
  },
  {
    "exchange": "prex",
    "moneda": "ARS",
    "monedaBase": "BRL",
    "compra": 310.3338,
    "venta": null
  },
  {
    "exchange": "lemon",
    "moneda": "ARS",
    "monedaBase": "BRL",
    "compra": 306.84,
    "venta": null
  },
  {
    "exchange": "plus",
    "moneda": "ARS",
    "monedaBase": "BRL",
    "compra": 302.78,
    "venta": null
  },
  {
    "exchange": "astropay",
    "moneda": "ARS",
    "monedaBase": "BRL",
    "compra": 301.01903956,
    "venta": null
  }
]