[
  {
    "exchange": "belo",
    "moneda": "USD",
    "monedaBase": "ARS",
    "criptomoneda": "USDT",
    "criptomonedaBase": null,
    "compra": 0.0006329113924050633,
    "venta": 0.000641025641025641
  },
  {
    "exchange": "belo",
    "moneda": "USD",
    "monedaBase": "ARS",
    "criptomoneda": "USDC",
    "criptomonedaBase": null,
    "compra": 0.0006315655609308256,
    "venta": 0.0006415908376422452
  },
  {
    "exchange": "belo",
    "moneda": "USD",
    "monedaBase": "ARS",
    "criptomoneda": "USD_AR",
    "criptomonedaBase": null,
    "compra": 0.0006455696202531646,
    "venta": 0.000673076923076923
  },
  {
    "exchange": "dolarapp",
    "moneda": "USD",
    "monedaBase": "ARS",
    "criptomoneda": "USDC",
    "criptomonedaBase": null,
    "compra": 0.0006380033048571191,
    "venta": 0.0006391884045854225
  },
  {
    "exchange": "satoshitango",
    "moneda": "USD",
    "monedaBase": "ARS",
    "criptomoneda": "USDT",
    "criptomonedaBase": null,
    "compra": 0.0006373120726025914,
    "venta": null
  },
  {
    "exchange": "satoshitango",
    "moneda": "USD",
    "monedaBase": "ARS",
    "criptomoneda": "USD",
    "criptomonedaBase": null,
    "compra": 0.0006780994229373911,
    "venta": null
  }
]