[
  {
    "exchange": "belo",
    "moneda": "ARS",
    "monedaBase": "PERt",
    "compra": 460.6060606060606,
    "venta": 435
  },
  {
    "exchange": "belo",
    "moneda": "BRAt",
    "monedaBase": "PERt",
    "compra": 1.5515151515151515,
    "venta": 1.4587
  },
  {
    "exchange": "belo",
    "moneda": "ARGt",
    "monedaBase": "PERt",
    "compra": 460.6060606060606,
    "venta": 435
  },
  {
    "exchange": "belo",
    "moneda": "MEXt",
    "monedaBase": "PERt",
    "compra": 5.27806207201172,
    "venta": 4.91425536785
  },
  {
    "exchange": "belo",
    "moneda": "CHLt",
    "monedaBase": "PERt",
    "compra": 273.0209218966015,
    "venta": 253.76868615
  },
  {
    "exchange": "belo",
    "moneda": "COLt",
    "monedaBase": "PERt",
    "compra": 1060.4070706372497,
    "venta": 977.36887953125
  },
  {
    "exchange": "belo",
    "moneda": "BOLt",
    "monedaBase": "PERt",
    "compra": 3.034431955641586,
    "venta": 2.81808750625
  },
  {
    "exchange": "belo",
    "moneda": "PERt",
    "monedaBase": "PERt",
    "compra": 1,
    "venta": 1
  }
]