[
  {
    "exchange": "belo",
    "moneda": "ARS",
    "monedaBase": "PERt",
    "compra": 456.969696969697,
    "venta": 432.1
  },
  {
    "exchange": "belo",
    "moneda": "BRAt",
    "monedaBase": "PERt",
    "compra": 1.5545454545454545,
    "venta": 1.4674
  },
  {
    "exchange": "belo",
    "moneda": "ARGt",
    "monedaBase": "PERt",
    "compra": 456.969696969697,
    "venta": 432.1
  },
  {
    "exchange": "belo",
    "moneda": "MEXt",
    "monedaBase": "PERt",
    "compra": 5.291570720690295,
    "venta": 4.92911708485
  },
  {
    "exchange": "belo",
    "moneda": "CHLt",
    "monedaBase": "PERt",
    "compra": 272.0381095164976,
    "venta": 252.89588388
  },
  {
    "exchange": "belo",
    "moneda": "COLt",
    "monedaBase": "PERt",
    "compra": 1059.3087343536176,
    "venta": 976.35081640625
  },
  {
    "exchange": "belo",
    "moneda": "BOLt",
    "monedaBase": "PERt",
    "compra": 3.006818368240921,
    "venta": 2.792442625
  },
  {
    "exchange": "belo",
    "moneda": "PERt",
    "monedaBase": "PERt",
    "compra": 1,
    "venta": 1
  }
]