[
  {
    "exchange": "belo",
    "moneda": "ARS",
    "monedaBase": "PERt",
    "compra": 464.24242424242425,
    "venta": 438.48
  },
  {
    "exchange": "belo",
    "moneda": "BRAt",
    "monedaBase": "PERt",
    "compra": 1.584848484848485,
    "venta": 1.4906
  },
  {
    "exchange": "belo",
    "moneda": "ARGt",
    "monedaBase": "PERt",
    "compra": 464.24242424242425,
    "venta": 438.48
  },
  {
    "exchange": "belo",
    "moneda": "MEXt",
    "monedaBase": "PERt",
    "compra": 5.31682227128157,
    "venta": 4.9531816343
  },
  {
    "exchange": "belo",
    "moneda": "CHLt",
    "monedaBase": "PERt",
    "compra": 277.63838731172007,
    "venta": 258.08706078
  },
  {
    "exchange": "belo",
    "moneda": "COLt",
    "monedaBase": "PERt",
    "compra": 1048.4492270987623,
    "venta": 966.33986234375
  },
  {
    "exchange": "belo",
    "moneda": "BOLt",
    "monedaBase": "PERt",
    "compra": 3.049772779728819,
    "venta": 2.8323346625
  },
  {
    "exchange": "belo",
    "moneda": "PERt",
    "monedaBase": "PERt",
    "compra": 1,
    "venta": 1
  }
]