[
  {
    "exchange": "belo",
    "moneda": "USD",
    "monedaBase": "BRAt",
    "criptomoneda": "USDT",
    "criptomonedaBase": null,
    "compra": 0.19493177387914232,
    "venta": 0.19801980198019803
  },
  {
    "exchange": "belo",
    "moneda": "USD",
    "monedaBase": "BRAt",
    "criptomoneda": "USDC",
    "criptomonedaBase": null,
    "compra": 0.19453476538459777,
    "venta": 0.19821222541757225
  },
  {
    "exchange": "belo",
    "moneda": "USD",
    "monedaBase": "BRAt",
    "criptomoneda": "USDT",
    "criptomonedaBase": null,
    "compra": 0.19493177387914232,
    "venta": 0.19801980198019803
  },
  {
    "exchange": "belo",
    "moneda": "USD",
    "monedaBase": "BRAt",
    "criptomoneda": "USDC",
    "criptomonedaBase": null,
    "compra": 0.19453476538459777,
    "venta": 0.19821222541757225
  }
]